omuchat/__init__.py
omuchat/chat.py
omuchat/client.py
omuchat/const.py
omuchat/permissions.py
omuchat/version.py
omuchat/event/__init__.py
omuchat/event/event.py
omuchat/event/event_types.py
omuchat/model/__init__.py
omuchat/model/author.py
omuchat/model/channel.py
omuchat/model/content.py
omuchat/model/gift.py
omuchat/model/message.py
omuchat/model/paid.py
omuchat/model/provider.py
omuchat/model/role.py
omuchat/model/room.py
omuchat-0.3.2.dist-info/METADATA
omuchat-0.3.2.dist-info/WHEEL
omuchat-0.3.2.dist-info/RECORD
