Metadata-Version: 2.3
Name: omuchat
Version: 0.3.2
Summary: Add your description here
Author-email: am230 <111672334+am230@users.noreply.github.com>
Requires-Python: >=3.12
Requires-Dist: loguru>=0.7.2
Requires-Dist: omu>=0.1.3
